<NewDataSet>
  

	<CITY>
		<STATE_ID>UP</STATE_ID>
		<CITY_ID>AGR</CITY_ID>
		<CITY_NAME>Agra</CITY_NAME>
	</CITY>
	<CITY>
		<STATE_ID>LD</STATE_ID>
		<CITY_ID>AGX</CITY_ID>
		<CITY_NAME>Agatti Island</CITY_NAME>
	</CITY>
	<CITY>
		<STATE_ID>MZ</STATE_ID>
		<CITY_ID>AJL</CITY_ID>
		<CITY_NAME>Aizawl</CITY_NAME>
	</CITY>
	<CITY>
		<STATE_ID>MH</STATE_ID>
		<CITY_ID>AKD</CITY_ID>
		<CITY_NAME>Akola</CITY_NAME>
	</CITY>
	<CITY>
		<STATE_ID>GJ</STATE_ID>
		<CITY_ID>AMD</CITY_ID>
		<CITY_NAME>Ahmedabad</CITY_NAME>
	</CITY>
	<CITY>
		<STATE_ID>PB</STATE_ID>
		<CITY_ID>ATQ</CITY_ID>
		<CITY_NAME>Amritsar</CITY_NAME>
	</CITY>
	<CITY>
		<STATE_ID>OR</STATE_ID>
		<CITY_ID>BBI</CITY_ID>
		<CITY_NAME>Bhubaneswar</CITY_NAME>
	</CITY>
	<CITY>
		<STATE_ID>GJ</STATE_ID>
		<CITY_ID>BDQ</CITY_ID>
		<CITY_NAME>Vadodara</CITY_NAME>
	</CITY>
	<CITY>
		<STATE_ID>UP</STATE_ID>
		<CITY_ID>BEK</CITY_ID>
		<CITY_NAME>Bareli</CITY_NAME>
	</CITY>
	<CITY>
		<STATE_ID>KA</STATE_ID>
		<CITY_ID>BEP</CITY_ID>
		<CITY_NAME>Bellary</CITY_NAME>
	</CITY>
	<CITY>
		<STATE_ID>GJ</STATE_ID>
		<CITY_ID>BHJ</CITY_ID>
		<CITY_NAME>Bhuj</CITY_NAME>
	</CITY>
	<CITY>
		<STATE_ID>MP</STATE_ID>
		<CITY_ID>BHO</CITY_ID>
		<CITY_NAME>Bhopal</CITY_NAME>
	</CITY>
	<CITY>
		<STATE_ID>GJ</STATE_ID>
		<CITY_ID>BHU</CITY_ID>
		<CITY_NAME>Bhavnagar</CITY_NAME>
	</CITY>
	<CITY>
		<STATE_ID>RJ</STATE_ID>
		<CITY_ID>BKB</CITY_ID>
		<CITY_NAME>Bikaner</CITY_NAME>
	</CITY>
	<CITY>
		<STATE_ID>KA</STATE_ID>
		<CITY_ID>BLR</CITY_ID>
		<CITY_NAME>Bangalore</CITY_NAME>
	</CITY>
	<CITY>
		<STATE_ID>MH</STATE_ID>
		<CITY_ID>BOM</CITY_ID>
		<CITY_NAME>Bombay (Mumbai)</CITY_NAME>
	</CITY>
	<CITY>
		<STATE_ID>PB</STATE_ID>
		<CITY_ID>BUP</CITY_ID>
		<CITY_NAME>Bhatinda</CITY_NAME>
	</CITY>
	<CITY>
		<STATE_ID>AN</STATE_ID>
		<CITY_ID>CBD</CITY_ID>
		<CITY_NAME>Car Nicobar</CITY_NAME>
	</CITY>
	<CITY>
		<STATE_ID>KL</STATE_ID>
		<CITY_ID>CCJ</CITY_ID>
		<CITY_NAME>Kozhikode</CITY_NAME>
	</CITY>
	<CITY>
		<STATE_ID>WB</STATE_ID>
		<CITY_ID>CCU</CITY_ID>
		<CITY_NAME>Calcutta (Kolkata)</CITY_NAME>
	</CITY>
	<CITY>
		<STATE_ID>AP</STATE_ID>
		<CITY_ID>CDP</CITY_ID>
		<CITY_NAME>Cuddapah</CITY_NAME>
	</CITY>
	<CITY>
		<STATE_ID>TN</STATE_ID>
		<CITY_ID>CJB</CITY_ID>
		<CITY_NAME>Coimbatore</CITY_NAME>
	</CITY>
	<CITY>
		<STATE_ID>WB</STATE_ID>
		<CITY_ID>COH</CITY_ID>
		<CITY_NAME>Cooch Behar</CITY_NAME>
	</CITY>
	<CITY>
		<STATE_ID>KL</STATE_ID>
		<CITY_ID>COK</CITY_ID>
		<CITY_NAME>Kochi</CITY_NAME>
	</CITY>
	<CITY>
		<STATE_ID>AR</STATE_ID>
		<CITY_ID>DAE</CITY_ID>
		<CITY_NAME>Daparizo</CITY_NAME>
	</CITY>
	<CITY>
		<STATE_ID>WB</STATE_ID>
		<CITY_ID>DAI</CITY_ID>
		<CITY_NAME>Darjeeling</CITY_NAME>
	</CITY>
	<CITY>
		<STATE_ID>JH</STATE_ID>
		<CITY_ID>DBD</CITY_ID>
		<CITY_NAME>Dhanbad</CITY_NAME>
	</CITY>
	<CITY>
		<STATE_ID>GA</STATE_ID>
		<CITY_ID>DBL</CITY_ID>
		<CITY_NAME>Panaji</CITY_NAME>
	</CITY>
	<CITY>
		<STATE_ID>DL</STATE_ID>
		<CITY_ID>DEL</CITY_ID>
		<CITY_NAME>Delhi</CITY_NAME>
	</CITY>
	<CITY>
		<STATE_ID>AR</STATE_ID>
		<CITY_ID>DEP</CITY_ID>
		<CITY_NAME>Deparizo</CITY_NAME>
	</CITY>
	<CITY>
		<STATE_ID>HP</STATE_ID>
		<CITY_ID>DHM</CITY_ID>
		<CITY_NAME>Dharamsala</CITY_NAME>
	</CITY>
	<CITY>
		<STATE_ID>AS</STATE_ID>
		<CITY_ID>DIB</CITY_ID>
		<CITY_NAME>Dibrugarh</CITY_NAME>
	</CITY>
	<CITY>
		<STATE_ID>DD</STATE_ID>
		<CITY_ID>DIU</CITY_ID>
		<CITY_NAME>Diu</CITY_NAME>
	</CITY>
	<CITY>
		<STATE_ID>NL</STATE_ID>
		<CITY_ID>DMU</CITY_ID>
		<CITY_NAME>Dimapur</CITY_NAME>
	</CITY>
	<CITY>
		<STATE_ID>AS</STATE_ID>
		<CITY_ID>GAU</CITY_ID>
		<CITY_NAME>Guwahati</CITY_NAME>
	</CITY>
	<CITY>
		<STATE_ID>BR</STATE_ID>
		<CITY_ID>GAY</CITY_ID>
		<CITY_NAME>Gaya</CITY_NAME>
	</CITY>
	<CITY>
		<STATE_ID>GA</STATE_ID>
		<CITY_ID>GOI</CITY_ID>
		<CITY_NAME>Goa</CITY_NAME>
	</CITY>
	<CITY>
		<STATE_ID>UP</STATE_ID>
		<CITY_ID>GOP</CITY_ID>
		<CITY_NAME>Gorakhpur</CITY_NAME>
	</CITY>
	<CITY>
		<STATE_ID>MP</STATE_ID>
		<CITY_ID>GUX</CITY_ID>
		<CITY_NAME>Guna</CITY_NAME>
	</CITY>
	<CITY>
		<STATE_ID>MP</STATE_ID>
		<CITY_ID>GWL</CITY_ID>
		<CITY_NAME>Gwalior</CITY_NAME>
	</CITY>
	<CITY>
		<STATE_ID>KA</STATE_ID>
		<CITY_ID>HBX</CITY_ID>
		<CITY_NAME>Hubli</CITY_NAME>
	</CITY>
	<CITY>
		<STATE_ID>MP</STATE_ID>
		<CITY_ID>HJR</CITY_ID>
		<CITY_NAME>Khajuraho</CITY_NAME>
	</CITY>
	<CITY>
		<STATE_ID>HR</STATE_ID>
		<CITY_ID>HSS</CITY_ID>
		<CITY_NAME>Hissar</CITY_NAME>
	</CITY>
	<CITY>
		<STATE_ID>AP</STATE_ID>
		<CITY_ID>HYD</CITY_ID>
		<CITY_NAME>Hyderabad</CITY_NAME>
	</CITY>
	<CITY>
		<STATE_ID>MP</STATE_ID>
		<CITY_ID>IDR</CITY_ID>
		<CITY_NAME>Indore</CITY_NAME>
	</CITY>
	<CITY>
		<STATE_ID>MN</STATE_ID>
		<CITY_ID>IMF</CITY_ID>
		<CITY_NAME>Imphal</CITY_NAME>
	</CITY>
	<CITY>
		<STATE_ID>MH</STATE_ID>
		<CITY_ID>ISK</CITY_ID>
		<CITY_NAME>Nasik</CITY_NAME>
	</CITY>
	<CITY>
		<STATE_ID>TR</STATE_ID>
		<CITY_ID>IXA</CITY_ID>
		<CITY_NAME>Agartala</CITY_NAME>
	</CITY>
	<CITY>
		<STATE_ID>WB</STATE_ID>
		<CITY_ID>IXB</CITY_ID>
		<CITY_NAME>Bagdogra</CITY_NAME>
	</CITY>
	<CITY>
		<STATE_ID>CH</STATE_ID>
		<CITY_ID>IXC</CITY_ID>
		<CITY_NAME>Chandigarh</CITY_NAME>
	</CITY>
	<CITY>
		<STATE_ID>UP</STATE_ID>
		<CITY_ID>IXD</CITY_ID>
		<CITY_NAME>Allahabad</CITY_NAME>
	</CITY>
	<CITY>
		<STATE_ID>KA</STATE_ID>
		<CITY_ID>IXE</CITY_ID>
		<CITY_NAME>Mangalore</CITY_NAME>
	</CITY>
	<CITY>
		<STATE_ID>KA</STATE_ID>
		<CITY_ID>IXG</CITY_ID>
		<CITY_NAME>Belgaum</CITY_NAME>
	</CITY>
	<CITY>
		<STATE_ID>TR</STATE_ID>
		<CITY_ID>IXH</CITY_ID>
		<CITY_NAME>Kailashahar</CITY_NAME>
	</CITY>
	<CITY>
		<STATE_ID>AS</STATE_ID>
		<CITY_ID>IXI</CITY_ID>
		<CITY_NAME>Lilabari</CITY_NAME>
	</CITY>
	<CITY>
		<STATE_ID>JK</STATE_ID>
		<CITY_ID>IXJ</CITY_ID>
		<CITY_NAME>Jammu</CITY_NAME>
	</CITY>
	<CITY>
		<STATE_ID>GJ</STATE_ID>
		<CITY_ID>IXK</CITY_ID>
		<CITY_NAME>Keshod</CITY_NAME>
	</CITY>
	<CITY>
		<STATE_ID>JK</STATE_ID>
		<CITY_ID>IXL</CITY_ID>
		<CITY_NAME>Leh</CITY_NAME>
	</CITY>
	<CITY>
		<STATE_ID>TN</STATE_ID>
		<CITY_ID>IXM</CITY_ID>
		<CITY_NAME>Madurai</CITY_NAME>
	</CITY>
	<CITY>
		<STATE_ID>TR</STATE_ID>
		<CITY_ID>IXN</CITY_ID>
		<CITY_NAME>Khowai</CITY_NAME>
	</CITY>
	<CITY>
		<STATE_ID>PB</STATE_ID>
		<CITY_ID>IXP</CITY_ID>
		<CITY_NAME>Pathankot</CITY_NAME>
	</CITY>
	<CITY>
		<STATE_ID>TR</STATE_ID>
		<CITY_ID>IXQ</CITY_ID>
		<CITY_NAME>Kamalpur</CITY_NAME>
	</CITY>
	<CITY>
		<STATE_ID>JH</STATE_ID>
		<CITY_ID>IXR</CITY_ID>
		<CITY_NAME>Ranchi</CITY_NAME>
	</CITY>
	<CITY>
		<STATE_ID>AS</STATE_ID>
		<CITY_ID>IXS</CITY_ID>
		<CITY_NAME>Silchar</CITY_NAME>
	</CITY>
	<CITY>
		<STATE_ID>AR</STATE_ID>
		<CITY_ID>IXT</CITY_ID>
		<CITY_NAME>Pasighat</CITY_NAME>
	</CITY>
	<CITY>
		<STATE_ID>MH</STATE_ID>
		<CITY_ID>IXU</CITY_ID>
		<CITY_NAME>Aurangabad</CITY_NAME>
	</CITY>
	<CITY>
		<STATE_ID>AR</STATE_ID>
		<CITY_ID>IXV</CITY_ID>
		<CITY_NAME>Along</CITY_NAME>
	</CITY>
	<CITY>
		<STATE_ID>JH</STATE_ID>
		<CITY_ID>IXW</CITY_ID>
		<CITY_NAME>Jamshedpur</CITY_NAME>
	</CITY>
	<CITY>
		<STATE_ID>GJ</STATE_ID>
		<CITY_ID>IXY</CITY_ID>
		<CITY_NAME>Kandla</CITY_NAME>
	</CITY>
	<CITY>
		<STATE_ID>AN</STATE_ID>
		<CITY_ID>IXZ</CITY_ID>
		<CITY_NAME>Port Blair</CITY_NAME>
	</CITY>
	<CITY>
		<STATE_ID>RJ</STATE_ID>
		<CITY_ID>JAI</CITY_ID>
		<CITY_NAME>Jaipur</CITY_NAME>
	</CITY>
	<CITY>
		<STATE_ID>RJ</STATE_ID>
		<CITY_ID>JDH</CITY_ID>
		<CITY_NAME>Jodhpur</CITY_NAME>
	</CITY>
	<CITY>
		<STATE_ID>GJ</STATE_ID>
		<CITY_ID>JGA</CITY_ID>
		<CITY_NAME>Jamnagar</CITY_NAME>
	</CITY>
	<CITY>
		<STATE_ID>CG</STATE_ID>
		<CITY_ID>JGB</CITY_ID>
		<CITY_NAME>Jagdalpur</CITY_NAME>
	</CITY>
	<CITY>
		<STATE_ID>MP</STATE_ID>
		<CITY_ID>JLR</CITY_ID>
		<CITY_NAME>Jabalpur</CITY_NAME>
	</CITY>
	<CITY>
		<STATE_ID>AS</STATE_ID>
		<CITY_ID>JRH</CITY_ID>
		<CITY_NAME>Jorhat</CITY_NAME>
	</CITY>
	<CITY>
		<STATE_ID>RJ</STATE_ID>
		<CITY_ID>JSA</CITY_ID>
		<CITY_NAME>Jaisalmer</CITY_NAME>
	</CITY>
	<CITY>
		<STATE_ID>MH</STATE_ID>
		<CITY_ID>KLH</CITY_ID>
		<CITY_NAME>Kolhapur</CITY_NAME>
	</CITY>
	<CITY>
		<STATE_ID>UP</STATE_ID>
		<CITY_ID>KNU</CITY_ID>
		<CITY_NAME>Kanpur</CITY_NAME>
	</CITY>
	<CITY>
		<STATE_ID>RJ</STATE_ID>
		<CITY_ID>KTU</CITY_ID>
		<CITY_NAME>Kota</CITY_NAME>
	</CITY>
	<CITY>
		<STATE_ID>HP</STATE_ID>
		<CITY_ID>KUU</CITY_ID>
		<CITY_NAME>Kulu</CITY_NAME>
	</CITY>
	<CITY>
		<STATE_ID>WB</STATE_ID>
		<CITY_ID>LDA</CITY_ID>
		<CITY_NAME>Malda</CITY_NAME>
	</CITY>
	<CITY>
		<STATE_ID>UP</STATE_ID>
		<CITY_ID>LKO</CITY_ID>
		<CITY_NAME>Lucknow</CITY_NAME>
	</CITY>
	<CITY>
		<STATE_ID>PB</STATE_ID>
		<CITY_ID>LUH</CITY_ID>
		<CITY_NAME>Ludhiana</CITY_NAME>
	</CITY>
	<CITY>
		<STATE_ID>TN</STATE_ID>
		<CITY_ID>MAA</CITY_ID>
		<CITY_NAME>Madras (Chennai)</CITY_NAME>
	</CITY>
	<CITY>
		<STATE_ID>AS</STATE_ID>
		<CITY_ID>MOH</CITY_ID>
		<CITY_NAME>Mohanbari</CITY_NAME>
	</CITY>
	<CITY>
		<STATE_ID>KA</STATE_ID>
		<CITY_ID>MYQ</CITY_ID>
		<CITY_NAME>Mysore</CITY_NAME>
	</CITY>
	<CITY>
		<STATE_ID>UP</STATE_ID>
		<CITY_ID>MZA</CITY_ID>
		<CITY_NAME>Muzaffarnagar</CITY_NAME>
	</CITY>
	<CITY>
		<STATE_ID>BR</STATE_ID>
		<CITY_ID>MZU</CITY_ID>
		<CITY_NAME>Muzaffarpur</CITY_NAME>
	</CITY>
	<CITY>
		<STATE_ID>MH</STATE_ID>
		<CITY_ID>NAG</CITY_ID>
		<CITY_NAME>Nagpur</CITY_NAME>
	</CITY>
	<CITY>
		<STATE_ID>MH</STATE_ID>
		<CITY_ID>NDC</CITY_ID>
		<CITY_NAME>Nanded</CITY_NAME>
	</CITY>
	<CITY>
		<STATE_ID>DD</STATE_ID>
		<CITY_ID>NMB</CITY_ID>
		<CITY_NAME>Daman</CITY_NAME>
	</CITY>
	<CITY>
		<STATE_ID>TN</STATE_ID>
		<CITY_ID>NVY</CITY_ID>
		<CITY_NAME>Neyveli</CITY_NAME>
	</CITY>
	<CITY>
		<STATE_ID>MH</STATE_ID>
		<CITY_ID>OMN</CITY_ID>
		<CITY_NAME>Osmanabad</CITY_NAME>
	</CITY>
	<CITY>
		<STATE_ID>MP</STATE_ID>
		<CITY_ID>PAB</CITY_ID>
		<CITY_NAME>Bilaspur</CITY_NAME>
	</CITY>
	<CITY>
		<STATE_ID>BR</STATE_ID>
		<CITY_ID>PAT</CITY_ID>
		<CITY_NAME>Patna</CITY_NAME>
	</CITY>
	<CITY>
		<STATE_ID>GJ</STATE_ID>
		<CITY_ID>PBD</CITY_ID>
		<CITY_NAME>Porbandar</CITY_NAME>
	</CITY>
	<CITY>
		<STATE_ID>UK</STATE_ID>
		<CITY_ID>PGH</CITY_ID>
		<CITY_NAME>Pantnagar</CITY_NAME>
	</CITY>
	<CITY>
		<STATE_ID>MH</STATE_ID>
		<CITY_ID>PNQ</CITY_ID>
		<CITY_NAME>Pune</CITY_NAME>
	</CITY>
	<CITY>
		<STATE_ID>PY</STATE_ID>
		<CITY_ID>PNY</CITY_ID>
		<CITY_NAME>Pondicherry</CITY_NAME>
	</CITY>
	<CITY>
		<STATE_ID>AP</STATE_ID>
		<CITY_ID>PUT</CITY_ID>
		<CITY_NAME>Puttaparthi</CITY_NAME>
	</CITY>
	<CITY>
		<STATE_ID>OR</STATE_ID>
		<CITY_ID>PYB</CITY_ID>
		<CITY_NAME>Jeypore</CITY_NAME>
	</CITY>
	<CITY>
		<STATE_ID>GJ</STATE_ID>
		<CITY_ID>QNB</CITY_ID>
		<CITY_NAME>Anand</CITY_NAME>
	</CITY>
	<CITY>
		<STATE_ID>HR</STATE_ID>
		<CITY_ID>QNF</CITY_ID>
		<CITY_NAME>Faridabad</CITY_NAME>
	</CITY>
	<CITY>
		<STATE_ID>PB</STATE_ID>
		<CITY_ID>QNW</CITY_ID>
		<CITY_NAME>Nawanshahar</CITY_NAME>
	</CITY>
	<CITY>
		<STATE_ID>GJ</STATE_ID>
		<CITY_ID>RAJ</CITY_ID>
		<CITY_NAME>Rajkot</CITY_NAME>
	</CITY>
	<CITY>
		<STATE_ID>MP</STATE_ID>
		<CITY_ID>REW</CITY_ID>
		<CITY_NAME>Rewa</CITY_NAME>
	</CITY>
	<CITY>
		<STATE_ID>WB</STATE_ID>
		<CITY_ID>RGH</CITY_ID>
		<CITY_NAME>Balurghat</CITY_NAME>
	</CITY>
	<CITY>
		<STATE_ID>AP</STATE_ID>
		<CITY_ID>RJA</CITY_ID>
		<CITY_NAME>Rajahmundry</CITY_NAME>
	</CITY>
	<CITY>
		<STATE_ID>JK</STATE_ID>
		<CITY_ID>RJI</CITY_ID>
		<CITY_NAME>Rajouri</CITY_NAME>
	</CITY>
	<CITY>
		<STATE_ID>AP</STATE_ID>
		<CITY_ID>RMD</CITY_ID>
		<CITY_NAME>Ramagundam</CITY_NAME>
	</CITY>
	<CITY>
		<STATE_ID>CG</STATE_ID>
		<CITY_ID>RPR</CITY_ID>
		<CITY_NAME>Raipur</CITY_NAME>
	</CITY>
	<CITY>
		<STATE_ID>OR</STATE_ID>
		<CITY_ID>RRK</CITY_ID>
		<CITY_NAME>Rourkela</CITY_NAME>
	</CITY>
	<CITY>
		<STATE_ID>MH</STATE_ID>
		<CITY_ID>RTC</CITY_ID>
		<CITY_NAME>Ratnagiri</CITY_NAME>
	</CITY>
	<CITY>
		<STATE_ID>AS</STATE_ID>
		<CITY_ID>RUP</CITY_ID>
		<CITY_NAME>Rupsi</CITY_NAME>
	</CITY>
	<CITY>
		<STATE_ID>ML</STATE_ID>
		<CITY_ID>SHL</CITY_ID>
		<CITY_NAME>Shillong</CITY_NAME>
	</CITY>
	<CITY>
		<STATE_ID>HP</STATE_ID>
		<CITY_ID>SLV</CITY_ID>
		<CITY_NAME>Simla</CITY_NAME>
	</CITY>
	<CITY>
		<STATE_ID>MH</STATE_ID>
		<CITY_ID>SSE</CITY_ID>
		<CITY_NAME>Sholapur</CITY_NAME>
	</CITY>
	<CITY>
		<STATE_ID>GJ</STATE_ID>
		<CITY_ID>STV</CITY_ID>
		<CITY_NAME>Surat</CITY_NAME>
	</CITY>
	<CITY>
		<STATE_ID>JK</STATE_ID>
		<CITY_ID>SXR</CITY_ID>
		<CITY_NAME>Srinagar</CITY_NAME>
	</CITY>
	<CITY>
		<STATE_ID>TN</STATE_ID>
		<CITY_ID>SXV</CITY_ID>
		<CITY_NAME>Salem</CITY_NAME>
	</CITY>
	<CITY>
		<STATE_ID>TN</STATE_ID>
		<CITY_ID>TCR</CITY_ID>
		<CITY_NAME>Tuticorin</CITY_NAME>
	</CITY>
	<CITY>
		<STATE_ID>AR</STATE_ID>
		<CITY_ID>TEI</CITY_ID>
		<CITY_NAME>Tezu</CITY_NAME>
	</CITY>
	<CITY>
		<STATE_ID>AS</STATE_ID>
		<CITY_ID>TEZ</CITY_ID>
		<CITY_NAME>Tezpur</CITY_NAME>
	</CITY>
	<CITY>
		<STATE_ID>AP</STATE_ID>
		<CITY_ID>TIR</CITY_ID>
		<CITY_NAME>Tirupati</CITY_NAME>
	</CITY>
	<CITY>
		<STATE_ID>TN</STATE_ID>
		<CITY_ID>TJV</CITY_ID>
		<CITY_NAME>Thanjavur</CITY_NAME>
	</CITY>
	<CITY>
		<STATE_ID>MP</STATE_ID>
		<CITY_ID>TNI</CITY_ID>
		<CITY_NAME>Satna</CITY_NAME>
	</CITY>
	<CITY>
		<STATE_ID>KL</STATE_ID>
		<CITY_ID>TRV</CITY_ID>
		<CITY_NAME>Thiruvananthapuram</CITY_NAME>
	</CITY>
	<CITY>
		<STATE_ID>TN</STATE_ID>
		<CITY_ID>TRZ</CITY_ID>
		<CITY_NAME>Tiruchirappally</CITY_NAME>
	</CITY>
	<CITY>
		<STATE_ID>RJ</STATE_ID>
		<CITY_ID>UDR</CITY_ID>
		<CITY_NAME>Udaipur</CITY_NAME>
	</CITY>
	<CITY>
		<STATE_ID>AP</STATE_ID>
		<CITY_ID>VGA</CITY_ID>
		<CITY_NAME>Vijayawada</CITY_NAME>
	</CITY>
	<CITY>
		<STATE_ID>UP</STATE_ID>
		<CITY_ID>VNS</CITY_ID>
		<CITY_NAME>Varanasi</CITY_NAME>
	</CITY>
	<CITY>
		<STATE_ID>AP</STATE_ID>
		<CITY_ID>VTZ</CITY_ID>
		<CITY_NAME>Visakhapatnam</CITY_NAME>
	</CITY>
	<CITY>
		<STATE_ID>AP</STATE_ID>
		<CITY_ID>WGC</CITY_ID>
		<CITY_NAME>Warangal</CITY_NAME>
	</CITY>
	<CITY>
		<STATE_ID>AR</STATE_ID>
		<CITY_ID>ZER</CITY_ID>
		<CITY_NAME>Zero</CITY_NAME>
	</CITY>
	<CITY>
		<STATE_ID>DL</STATE_ID>
		<CITY_ID>GGN</CITY_ID>
		<CITY_NAME>Gurgaon</CITY_NAME>
	</CITY>
	<CITY>
		<STATE_ID>DL</STATE_ID>
		<CITY_ID>NOD</CITY_ID>
		<CITY_NAME>Noida</CITY_NAME>
	</CITY>
	<CITY>
		<STATE_ID>KL</STATE_ID>
		<CITY_ID>EDL</CITY_ID>
		<CITY_NAME>Edappal</CITY_NAME>
	</CITY>
	<CITY>
		<STATE_ID>KL</STATE_ID>
		<CITY_ID>KNR</CITY_ID>
		<CITY_NAME>Kannur</CITY_NAME>
	</CITY>
	<CITY>
		<STATE_ID>KL</STATE_ID>
		<CITY_ID>KSD</CITY_ID>
		<CITY_NAME>Kasargode</CITY_NAME>
	</CITY>
	<CITY>
		<STATE_ID>KL</STATE_ID>
		<CITY_ID>KYM</CITY_ID>
		<CITY_NAME>Kottayam</CITY_NAME>
	</CITY>
	<CITY>
		<STATE_ID>PB</STATE_ID>
		<CITY_ID>QJU</CITY_ID>
		<CITY_NAME>Jalandhar</CITY_NAME>
	</CITY>
	<CITY>
		<STATE_ID>TN</STATE_ID>
		<CITY_ID>NGL</CITY_ID>
		<CITY_NAME>Nagarcoil</CITY_NAME>
	</CITY>
	<CITY>
		<STATE_ID>UP</STATE_ID>
		<CITY_ID>GZB</CITY_ID>
		<CITY_NAME>Gazhiabad</CITY_NAME>
	</CITY>
	<CITY>
		<STATE_ID>UP</STATE_ID>
		<CITY_ID>MTC</CITY_ID>
		<CITY_NAME>Meerut</CITY_NAME>
	</CITY>
	<CITY>
		<STATE_ID>UT</STATE_ID>
		<CITY_ID>DED</CITY_ID>
		<CITY_NAME>Deharadun</CITY_NAME>
	</CITY>
	<CITY>
		<STATE_ID>37</STATE_ID>
		<CITY_ID>DFW</CITY_ID>
		<CITY_NAME>Dallas</CITY_NAME>
	</CITY>
	<CITY>
		<STATE_ID>PR</STATE_ID>
		<CITY_ID>PAR</CITY_ID>
		<CITY_NAME>PARO</CITY_NAME>
	</CITY>
	<CITY>
		<STATE_ID>PR</STATE_ID>
		<CITY_ID>THI</CITY_ID>
		<CITY_NAME>THIMPU</CITY_NAME>
	</CITY>
	<CITY>
		<STATE_ID>AP</STATE_ID>
		<CITY_ID>IRR</CITY_ID>
		<CITY_NAME>Iriss</CITY_NAME>
	</CITY>
  
  
 
   
</NewDataSet>

